RCAIDE/VERSION
RCAIDE/Vehicle.py
RCAIDE/__init__.py
RCAIDE/load.py
RCAIDE/save.py
RCAIDE/Framework/__init__.py
RCAIDE/Framework/Analyses/Analysis.py
RCAIDE/Framework/Analyses/Process.py
RCAIDE/Framework/Analyses/Settings.py
RCAIDE/Framework/Analyses/Vehicle.py
RCAIDE/Framework/Analyses/__init__.py
RCAIDE/Framework/Analyses/Aerodynamics/Aerodynamics.py
RCAIDE/Framework/Analyses/Aerodynamics/Athena_Vortex_Lattice.py
RCAIDE/Framework/Analyses/Aerodynamics/Vortex_Lattice_Method.py
RCAIDE/Framework/Analyses/Aerodynamics/__init__.py
RCAIDE/Framework/Analyses/Atmospheric/Atmospheric.py
RCAIDE/Framework/Analyses/Atmospheric/Constant_Temperature.py
RCAIDE/Framework/Analyses/Atmospheric/US_Standard_1976.py
RCAIDE/Framework/Analyses/Atmospheric/__init__.py
RCAIDE/Framework/Analyses/Common/Process_Geometry.py
RCAIDE/Framework/Analyses/Common/__init__.py
RCAIDE/Framework/Analyses/Emissions/Emission_Index_CRN_Method.py
RCAIDE/Framework/Analyses/Emissions/Emission_Index_Correlation_Method.py
RCAIDE/Framework/Analyses/Emissions/Emissions.py
RCAIDE/Framework/Analyses/Emissions/__init__.py
RCAIDE/Framework/Analyses/Energy/Energy.py
RCAIDE/Framework/Analyses/Energy/__init__.py
RCAIDE/Framework/Analyses/Geodesics/Geodesics.py
RCAIDE/Framework/Analyses/Geodesics/__init__.py
RCAIDE/Framework/Analyses/Noise/Correlation_Buildup.py
RCAIDE/Framework/Analyses/Noise/Frequency_Domain_Buildup.py
RCAIDE/Framework/Analyses/Noise/Noise.py
RCAIDE/Framework/Analyses/Noise/__init__.py
RCAIDE/Framework/Analyses/Planets/Earth.py
RCAIDE/Framework/Analyses/Planets/Planet.py
RCAIDE/Framework/Analyses/Planets/__init__.py
RCAIDE/Framework/Analyses/Propulsion/Ducted_Fan_Design_Code.py
RCAIDE/Framework/Analyses/Propulsion/__init__.py
RCAIDE/Framework/Analyses/Stability/Athena_Vortex_Lattice.py
RCAIDE/Framework/Analyses/Stability/Stability.py
RCAIDE/Framework/Analyses/Stability/Vortex_Lattice_Method.py
RCAIDE/Framework/Analyses/Stability/__init__.py
RCAIDE/Framework/Analyses/Weights/Conventional.py
rcaide_leads-1.2.1.dist-info/licenses/LICENSE
rcaide_leads-1.2.1.dist-info/METADATA
rcaide_leads-1.2.1.dist-info/WHEEL
rcaide_leads-1.2.1.dist-info/top_level.txt
rcaide_leads-1.2.1.dist-info/RECORD
